PythonQueryLanguage/__init__.py
PythonQueryLanguage/pql.py
pythonquerylanguage-0.1.8.dist-info/METADATA
pythonquerylanguage-0.1.8.dist-info/WHEEL
pythonquerylanguage-0.1.8.dist-info/RECORD
